openwrt_mcp/__init__.py
openwrt_mcp/openwrt.py
openwrt_mcp-0.1.7.dist-info/METADATA
openwrt_mcp-0.1.7.dist-info/WHEEL
openwrt_mcp-0.1.7.dist-info/entry_points.txt
openwrt_mcp-0.1.7.dist-info/top_level.txt
openwrt_mcp-0.1.7.dist-info/RECORD
