Metadata-Version: 2.4
Name: openwrt-mcp
Version: 0.1.7
Summary: A MCP server for OpenWrt devices. This is a very early version and may contain unexpected errors.
Requires-Python: >=3.10
Requires-Dist: fastmcp>=2.10.6
Requires-Dist: requests>=2.32.4
